<?xml version="1.0"?>
<cena version="0.8.2"><result judgetime="44860.6068991204"><problem title="hidden" filename="hidden\hidden.cpp" status="1" hash="2404252035" detail=""><testcase status="7" exitcode="0" detail="" time="0" memory="20804" score="10"/><testcase status="7" exitcode="0" detail="" time="0" memory="20804" score="10"/><testcase status="7" exitcode="0" detail="" time="0" memory="20804" score="10"/><testcase status="7" exitcode="0" detail="" time="0" memory="20804" score="10"/><testcase status="7" exitcode="0" detail="" time="0" memory="20804" score="10"/><testcase status="7" exitcode="0" detail="" time="0" memory="20876" score="10"/><testcase status="7" exitcode="0" detail="" time="0" memory="20880" score="10"/><testcase status="7" exitcode="0" detail="" time="0.01" memory="20880" score="10"/><testcase status="7" exitcode="0" detail="" time="0.01" memory="20876" score="10"/><testcase status="7" exitcode="0" detail="" time="0" memory="20880" score="10"/></problem><problem title="brackets" filename="brackets\brackets.cpp" status="1" hash="3537591414" detail=""><testcase status="7" exitcode="0" detail="" time="0" memory="1376" score="10"/><testcase status="7" exitcode="0" detail="" time="0" memory="1376" score="10"/><testcase status="7" exitcode="0" detail="" time="0" memory="1376" score="10"/><testcase status="7" exitcode="0" detail="" time="0" memory="1376" score="10"/><testcase status="7" exitcode="0" detail="" time="0" memory="1376" score="10"/><testcase status="7" exitcode="0" detail="" time="0.32" memory="1388" score="10"/><testcase status="7" exitcode="0" detail="" time="0.29" memory="1392" score="10"/><testcase status="7" exitcode="0" detail="" time="0.31" memory="1384" score="10"/><testcase status="7" exitcode="0" detail="" time="0.31" memory="1388" score="10"/><testcase status="7" exitcode="0" detail="" time="0.29" memory="1388" score="10"/></problem><problem title="toy" filename="toy\toy.cpp" status="1" hash="3420736008" detail=""><testcase status="7" exitcode="0" detail="" time="0" memory="2352" score="5"/><testcase status="7" exitcode="0" detail="" time="0" memory="2356" score="5"/><testcase status="7" exitcode="0" detail="" time="0" memory="2356" score="5"/><testcase status="7" exitcode="0" detail="" time="0" memory="2356" score="5"/><testcase status="7" exitcode="0" detail="" time="0" memory="2352" score="5"/><testcase status="7" exitcode="0" detail="" time="0" memory="2352" score="5"/><testcase status="7" exitcode="0" detail="" time="0" memory="2352" score="5"/><testcase status="7" exitcode="0" detail="" time="0" memory="2352" score="5"/><testcase status="7" exitcode="0" detail="" time="0" memory="2352" score="5"/><testcase status="7" exitcode="0" detail="" time="0" memory="2352" score="5"/><testcase status="7" exitcode="0" detail="" time="0" memory="2356" score="5"/><testcase status="7" exitcode="0" detail="" time="0" memory="2352" score="5"/><testcase status="7" exitcode="0" detail="" time="0" memory="2352" score="5"/><testcase status="7" exitcode="0" detail="" time="0" memory="2352" score="5"/><testcase status="7" exitcode="0" detail="" time="0" memory="2352" score="5"/><testcase status="7" exitcode="0" detail="" time="0" memory="2352" score="5"/><testcase status="7" exitcode="0" detail="" time="0.34" memory="2352" score="5"/><testcase status="7" exitcode="0" detail="" time="0.34" memory="2352" score="5"/><testcase status="7" exitcode="0" detail="" time="0.34" memory="2356" score="5"/><testcase status="7" exitcode="0" detail="" time="0.34" memory="2352" score="5"/></problem><problem title="queue" filename="queue\queue.cpp" status="1" hash="4294424484" detail=""><testcase status="7" exitcode="0" detail="" time="0" memory="1572" score="10"/><testcase status="7" exitcode="0" detail="" time="0" memory="1572" score="10"/><testcase status="7" exitcode="0" detail="" time="0.01" memory="1572" score="10"/><testcase status="7" exitcode="0" detail="" time="0" memory="1572" score="10"/><testcase status="7" exitcode="0" detail="" time="0" memory="1572" score="10"/><testcase status="7" exitcode="0" detail="" time="0" memory="1572" score="10"/><testcase status="7" exitcode="0" detail="" time="0.14" memory="1572" score="10"/><testcase status="7" exitcode="0" detail="" time="0.15" memory="1572" score="10"/><testcase status="7" exitcode="0" detail="" time="0.15" memory="1572" score="10"/><testcase status="7" exitcode="0" detail="" time="0.15" memory="1572" score="10"/></problem></result></cena>
